axeman/__init__.py
axeman/certlib.py
axeman/core.py
gantiAxeman-1.15.5.dist-info/LICENSE
gantiAxeman-1.15.5.dist-info/METADATA
gantiAxeman-1.15.5.dist-info/WHEEL
gantiAxeman-1.15.5.dist-info/entry_points.txt
gantiAxeman-1.15.5.dist-info/top_level.txt
gantiAxeman-1.15.5.dist-info/RECORD
