Metadata-Version: 2.1
Name: gantiAxeman
Version: 1.15.5
Summary: This is a form of https://github.com/CaliDog/Axeman/
Home-page: https://github.com/ganti/Axeman/
Author: Ganti
License: MIT
Classifier: License :: OSI Approved :: MIT License
Classifier: Topic :: Internet :: WWW/HTTP
Classifier: Topic :: Software Development :: Testing
Classifier: Environment :: Console
Classifier: Operating System :: MacOS :: MacOS X
Classifier: Operating System :: POSIX
Classifier: Programming Language :: Python :: 3
Classifier: Programming Language :: Python :: 3.5
Classifier: Programming Language :: Python :: 3.6
License-File: LICENSE
Requires-Dist: asyncio
Requires-Dist: uvloop
Requires-Dist: aiohttp
Requires-Dist: aioprocessing
Requires-Dist: PyOpenSSL
Requires-Dist: construct (==2.9.52)
